LucaZeitRechner/Arbeitszeitrechner.py
LucaZeitRechner/TimeCalcModule.py
LucaZeitRechner/WorkTimeCalc.py
LucaZeitRechner/__init__.py
LucaZeitRechner/main.py
Arbeitszeitrechner-1.0.dist-info/METADATA
Arbeitszeitrechner-1.0.dist-info/WHEEL
Arbeitszeitrechner-1.0.dist-info/entry_points.txt
Arbeitszeitrechner-1.0.dist-info/top_level.txt
Arbeitszeitrechner-1.0.dist-info/RECORD
